products_crawler/__init__.py
products_crawler/itemloaders.py
products_crawler/items.py
products_crawler/middlewares.py
products_crawler/pipelines.py
products_crawler/processors.py
products_crawler/settings.py
products_crawler/utils.py
products_crawler/spider_configs/__init__.py
products_crawler/spider_configs/bearbrick.json
products_crawler/spider_configs/glld.json
products_crawler/spider_configs/kapital.json
products_crawler/spider_configs/nike.json
products_crawler/spider_configs/supreme.json
products_crawler/spider_configs/ts.json
products_crawler/spider_configs/uastore.json
products_crawler/spiders/__init__.py
products_crawler/spiders/bearbrick.py
products_crawler/spiders/glld.py
products_crawler/spiders/kapital.py
products_crawler/spiders/nike.py
products_crawler/spiders/supreme.py
products_crawler/spiders/ts.py
products_crawler/spiders/uastore.py
products_crawler-0.1.9.dist-info/LICENSE
products_crawler-0.1.9.dist-info/METADATA
products_crawler-0.1.9.dist-info/WHEEL
products_crawler-0.1.9.dist-info/entry_points.txt
products_crawler-0.1.9.dist-info/top_level.txt
products_crawler-0.1.9.dist-info/RECORD
