Metadata-Version: 2.1
Name: products-crawler
Version: 0.1.9
Summary: A scrapy project for crawl product pictures and information.
Home-page: https://github.com/RyouMon/ProductCrawler
Author: RyouMon
Author-email: wenslife@outlook.com
Project-URL: Bug Tracker, https://github.com/RyouMon/ProductCrawler/issues
Classifier: Programming Language :: Python :: 3
Classifier: License :: OSI Approved :: MIT License
Classifier: Operating System :: OS Independent
Requires-Python: >=3.6
License-File: LICENSE
Requires-Dist: fake-useragent (==0.1.11)
Requires-Dist: Scrapy (==2.6.1)
Requires-Dist: selenium (==3.141.0)
